{
  "@id": "https://repo.metadatacenter.org/template-elements/503cb864-0694-4765-960a-a12b3b2846b9",
  "@type": "https://schema.metadatacenter.org/core/TemplateElement",
  "@context": {
    "xsd": "http://www.w3.org/2001/XMLSchema#",
    "pav": "http://purl.org/pav/",
    "bibo": "http://purl.org/ontology/bibo/",
    "oslc": "http://open-services.net/ns/core#",
    "schema": "http://schema.org/",
    "schema:name": {
      "@type": "xsd:string"
    },
    "schema:description": {
      "@type": "xsd:string"
    },
    "pav:createdOn": {
      "@type": "xsd:dateTime"
    },
    "pav:createdBy": {
      "@type": "@id"
    },
    "pav:lastUpdatedOn": {
      "@type": "xsd:dateTime"
    },
    "oslc:modifiedBy": {
      "@type": "@id"
    }
  },
  "type": "object",
  "title": "Spatialcoverage element schema",
  "description": "Spatialcoverage element schema generated by the CEDAR Template Editor 2.5.11",
  "_ui": {
    "order": [
      "SpatialCoverageBoundingBox",
      "SpatialCoveragePoints",
      "SpatialCoveragePolygon",
      "GeoLocations"
    ],
    "propertyLabels": {
      "SpatialCoveragePoints": "SpatialCoveragePoints",
      "SpatialCoverageBoundingBox": "SpatialCoverageBoundingBox",
      "SpatialCoveragePolygon": "SpatialCoveragePolygon",
      "GeoLocations": "GeoLocations"
    },
    "propertyDescriptions": {
      "SpatialCoveragePoints": "The geospatial area (region on Earth) covered by the dataset being described.",
      "SpatialCoverageBoundingBox": "The geospatial area (region on Earth) covered by the dataset being described.",
      "SpatialCoveragePolygon": "The geospatial area (region on Earth) covered by the dataset described by a polygon.",
      "GeoLocations": "Geo locations which are covered by the dataset being described."
    }
  },
  "properties": {
    "@context": {
      "type": "object",
      "properties": {
        "SpatialCoveragePoints": {
          "enum": [
            "https://schema.metadatacenter.org/properties/c28778ae-dd54-43bb-861e-b08b062b53ef"
          ]
        },
        "SpatialCoverageBoundingBox": {
          "enum": [
            "https://schema.metadatacenter.org/properties/964affd1-91f8-4f96-8b4e-1dec30380626"
          ]
        },
        "SpatialCoveragePolygon": {
          "enum": [
            "https://schema.metadatacenter.org/properties/e531d328-5728-4b36-a79a-90be8464c175"
          ]
        },
        "GeoLocations": {
          "enum": [
            "https://schema.metadatacenter.org/properties/60fa162c-5147-43b3-885b-6865fca3d0d4"
          ]
        }
      },
      "additionalProperties": false,
      "required": [
        "SpatialCoveragePoints",
        "SpatialCoverageBoundingBox",
        "SpatialCoveragePolygon",
        "GeoLocations"
      ]
    },
    "@id": {
      "type": "string",
      "format": "uri"
    },
    "@type": {
      "oneOf": [
        {
          "type": "string",
          "format": "uri"
        },
        {
          "type": "array",
          "minItems": 1,
          "items": {
            "type": "string",
            "format": "uri"
          },
          "uniqueItems": true
        }
      ]
    },
    "SpatialCoveragePoints": {
      "type": "array",
      "minItems": 0,
      "items": {
        "type": "object",
        "@id": "https://repo.metadatacenter.org/template-elements/d89927c0-4708-4845-b31c-4ce3e6b2a068",
        "@type": "https://schema.metadatacenter.org/core/TemplateElement",
        "@context": {
          "xsd": "http://www.w3.org/2001/XMLSchema#",
          "pav": "http://purl.org/pav/",
          "bibo": "http://purl.org/ontology/bibo/",
          "oslc": "http://open-services.net/ns/core#",
          "schema": "http://schema.org/",
          "schema:name": {
            "@type": "xsd:string"
          },
          "schema:description": {
            "@type": "xsd:string"
          },
          "pav:createdOn": {
            "@type": "xsd:dateTime"
          },
          "pav:createdBy": {
            "@type": "@id"
          },
          "pav:lastUpdatedOn": {
            "@type": "xsd:dateTime"
          },
          "oslc:modifiedBy": {
            "@type": "@id"
          }
        },
        "title": "SpatialCoveragePoints field schema",
        "description": "SpatialCoveragePoints field schema generated by the CEDAR Template Editor 2.5.11",
        "_ui": {
          "order": [
            "pointLongitude",
            "pointLatitude"
          ],
          "propertyLabels": {
            "pointLongitude": "pointLongitude",
            "pointLatitude": "pointLatitude"
          },
          "propertyDescriptions": {
            "pointLongitude": "Geographic longitude of a point which represents a location of dataset collection.",
            "pointLatitude": "Geographic latitude of a point which represents a location of dataset collection."
          }
        },
        "properties": {
          "@context": {
            "type": "object",
            "properties": {
              "pointLongitude": {
                "enum": [
                  "https://schema.metadatacenter.org/properties/4ba6f1f3-3895-40ae-90b5-0eb44e972c6d"
                ]
              },
              "pointLatitude": {
                "enum": [
                  "https://schema.metadatacenter.org/properties/f30f9128-f56d-4183-9b93-66b6349a2c40"
                ]
              }
            },
            "additionalProperties": false,
            "required": [
              "pointLongitude",
              "pointLatitude"
            ]
          },
          "@id": {
            "type": "string",
            "format": "uri"
          },
          "@type": {
            "oneOf": [
              {
                "type": "string",
                "format": "uri"
              },
              {
                "type": "array",
                "minItems": 1,
                "items": {
                  "type": "string",
                  "format": "uri"
                },
                "uniqueItems": true
              }
            ]
          },
          "pointLongitude": {
            "@type": "https://schema.metadatacenter.org/core/TemplateField",
            "@context": {
              "xsd": "http://www.w3.org/2001/XMLSchema#",
              "pav": "http://purl.org/pav/",
              "bibo": "http://purl.org/ontology/bibo/",
              "oslc": "http://open-services.net/ns/core#",
              "schema": "http://schema.org/",
              "skos": "http://www.w3.org/2004/02/skos/core#",
              "schema:name": {
                "@type": "xsd:string"
              },
              "schema:description": {
                "@type": "xsd:string"
              },
              "skos:prefLabel": {
                "@type": "xsd:string"
              },
              "skos:altLabel": {
                "@type": "xsd:string"
              },
              "pav:createdOn": {
                "@type": "xsd:dateTime"
              },
              "pav:createdBy": {
                "@type": "@id"
              },
              "pav:lastUpdatedOn": {
                "@type": "xsd:dateTime"
              },
              "oslc:modifiedBy": {
                "@type": "@id"
              }
            },
            "type": "object",
            "title": "pointLongitude field schema",
            "description": "pointLongitude field schema generated by the CEDAR Template Editor 2.5.11",
            "_ui": {
              "inputType": "textfield"
            },
            "_valueConstraints": {
              "requiredValue": true
            },
            "properties": {
              "@type": {
                "oneOf": [
                  {
                    "type": "string",
                    "format": "uri"
                  },
                  {
                    "type": "array",
                    "minItems": 1,
                    "items": {
                      "type": "string",
                      "format": "uri"
                    },
                    "uniqueItems": true
                  }
                ]
              },
              "@value": {
                "type": [
                  "string",
                  "null"
                ]
              },
              "rdfs:label": {
                "type": [
                  "string",
                  "null"
                ]
              }
            },
            "required": [
              "@value"
            ],
            "schema:name": "pointLongitude",
            "schema:description": "Geographic longitude of a point which represents a location of dataset collection.",
            "pav:createdOn": "2020-10-20T09:46:22-07:00",
            "pav:createdBy": "https://metadatacenter.org/users/cb584e9d-cd34-44f0-9d67-10b217311750",
            "pav:lastUpdatedOn": "2020-10-20T09:46:22-07:00",
            "oslc:modifiedBy": "https://metadatacenter.org/users/cb584e9d-cd34-44f0-9d67-10b217311750",
            "schema:schemaVersion": "1.6.0",
            "additionalProperties": false,
            "skos:prefLabel": "pointLongitude",
            "@id": "https://repo.metadatacenter.org/template-fields/2990d00b-1475-46d8-9116-e4e7e8349ac5",
            "$schema": "http://json-schema.org/draft-04/schema#"
          },
          "pointLatitude": {
            "@type": "https://schema.metadatacenter.org/core/TemplateField",
            "@context": {
              "xsd": "http://www.w3.org/2001/XMLSchema#",
              "pav": "http://purl.org/pav/",
              "bibo": "http://purl.org/ontology/bibo/",
              "oslc": "http://open-services.net/ns/core#",
              "schema": "http://schema.org/",
              "skos": "http://www.w3.org/2004/02/skos/core#",
              "schema:name": {
                "@type": "xsd:string"
              },
              "schema:description": {
                "@type": "xsd:string"
              },
              "skos:prefLabel": {
                "@type": "xsd:string"
              },
              "skos:altLabel": {
                "@type": "xsd:string"
              },
              "pav:createdOn": {
                "@type": "xsd:dateTime"
              },
              "pav:createdBy": {
                "@type": "@id"
              },
              "pav:lastUpdatedOn": {
                "@type": "xsd:dateTime"
              },
              "oslc:modifiedBy": {
                "@type": "@id"
              }
            },
            "type": "object",
            "title": "pointLatitude field schema",
            "description": "pointLatitude field schema generated by the CEDAR Template Editor 2.5.11",
            "_ui": {
              "inputType": "textfield"
            },
            "_valueConstraints": {
              "requiredValue": true
            },
            "properties": {
              "@type": {
                "oneOf": [
                  {
                    "type": "string",
                    "format": "uri"
                  },
                  {
                    "type": "array",
                    "minItems": 1,
                    "items": {
                      "type": "string",
                      "format": "uri"
                    },
                    "uniqueItems": true
                  }
                ]
              },
              "@value": {
                "type": [
                  "string",
                  "null"
                ]
              },
              "rdfs:label": {
                "type": [
                  "string",
                  "null"
                ]
              }
            },
            "required": [
              "@value"
            ],
            "schema:name": "pointLatitude",
            "schema:description": "Geographic latitude of a point which represents a location of dataset collection.",
            "pav:createdOn": "2020-10-20T09:46:22-07:00",
            "pav:createdBy": "https://metadatacenter.org/users/cb584e9d-cd34-44f0-9d67-10b217311750",
            "pav:lastUpdatedOn": "2020-10-20T09:46:22-07:00",
            "oslc:modifiedBy": "https://metadatacenter.org/users/cb584e9d-cd34-44f0-9d67-10b217311750",
            "schema:schemaVersion": "1.6.0",
            "additionalProperties": false,
            "skos:prefLabel": "pointLatitude",
            "@id": "https://repo.metadatacenter.org/template-fields/6ba76c6e-9f3a-46a0-b625-acb57f8c1716",
            "$schema": "http://json-schema.org/draft-04/schema#"
          }
        },
        "required": [
          "@context",
          "@id",
          "pointLongitude",
          "pointLatitude"
        ],
        "additionalProperties": false,
        "pav:createdOn": "2020-10-20T09:54:21-07:00",
        "pav:createdBy": "https://metadatacenter.org/users/cb584e9d-cd34-44f0-9d67-10b217311750",
        "pav:lastUpdatedOn": "2020-10-20T09:54:21-07:00",
        "oslc:modifiedBy": "https://metadatacenter.org/users/cb584e9d-cd34-44f0-9d67-10b217311750",
        "schema:schemaVersion": "1.6.0",
        "schema:name": "SpatialCoveragePoints",
        "schema:description": "The geospatial area (region on Earth) covered by the dataset being described.",
        "pav:version": "0.0.1",
        "bibo:status": "bibo:draft",
        "$schema": "http://json-schema.org/draft-04/schema#"
      }
    },
    "SpatialCoverageBoundingBox": {
      "type": "array",
      "minItems": 0,
      "maxItems": 1,
      "items": {
        "type": "object",
        "@id": "https://repo.metadatacenter.org/template-elements/6e614cc0-2998-416a-a999-5dd1764dc750",
        "@type": "https://schema.metadatacenter.org/core/TemplateElement",
        "@context": {
          "xsd": "http://www.w3.org/2001/XMLSchema#",
          "pav": "http://purl.org/pav/",
          "bibo": "http://purl.org/ontology/bibo/",
          "oslc": "http://open-services.net/ns/core#",
          "schema": "http://schema.org/",
          "schema:name": {
            "@type": "xsd:string"
          },
          "schema:description": {
            "@type": "xsd:string"
          },
          "pav:createdOn": {
            "@type": "xsd:dateTime"
          },
          "pav:createdBy": {
            "@type": "@id"
          },
          "pav:lastUpdatedOn": {
            "@type": "xsd:dateTime"
          },
          "oslc:modifiedBy": {
            "@type": "@id"
          }
        },
        "title": "SpatialCoverageBoundingBox field schema",
        "description": "SpatialCoverageBoundingBox field schema generated by the CEDAR Template Editor 2.5.11",
        "_ui": {
          "order": [
            "westBoundLongitude",
            "eastBoundLongitude",
            "southBoundLatitude",
            "northBoundLatitude"
          ],
          "propertyLabels": {
            "westBoundLongitude": "westBoundLongitude",
            "eastBoundLongitude": "eastBoundLongitude",
            "southBoundLatitude": "southBoundLatitude",
            "northBoundLatitude": "northBoundLatitude"
          },
          "propertyDescriptions": {
            "westBoundLongitude": "The most west longitude of a bounding box representing an area of dataset collection.",
            "eastBoundLongitude": "The most east longitude of a bounding box representing an area of dataset collection.",
            "southBoundLatitude": "The most south latitude of a bounding box representing an area of dataset collection.",
            "northBoundLatitude": "The most north latitude of a bounding box representing an area of dataset collection."
          }
        },
        "properties": {
          "@context": {
            "type": "object",
            "properties": {
              "westBoundLongitude": {
                "enum": [
                  "https://schema.metadatacenter.org/properties/c2dd4063-f358-4b71-a04d-2347a913b419"
                ]
              },
              "eastBoundLongitude": {
                "enum": [
                  "https://schema.metadatacenter.org/properties/0bbb281d-cfef-419d-9dd3-4a1c0dbb4ddd"
                ]
              },
              "southBoundLatitude": {
                "enum": [
                  "https://schema.metadatacenter.org/properties/640d8fc1-f1d9-4383-9ee2-64013a965573"
                ]
              },
              "northBoundLatitude": {
                "enum": [
                  "https://schema.metadatacenter.org/properties/4b422dc1-f187-4877-aa65-ee3e482b96e6"
                ]
              }
            },
            "additionalProperties": false,
            "required": [
              "westBoundLongitude",
              "eastBoundLongitude",
              "southBoundLatitude",
              "northBoundLatitude"
            ]
          },
          "@id": {
            "type": "string",
            "format": "uri"
          },
          "@type": {
            "oneOf": [
              {
                "type": "string",
                "format": "uri"
              },
              {
                "type": "array",
                "minItems": 1,
                "items": {
                  "type": "string",
                  "format": "uri"
                },
                "uniqueItems": true
              }
            ]
          },
          "westBoundLongitude": {
            "@type": "https://schema.metadatacenter.org/core/TemplateField",
            "@context": {
              "xsd": "http://www.w3.org/2001/XMLSchema#",
              "pav": "http://purl.org/pav/",
              "bibo": "http://purl.org/ontology/bibo/",
              "oslc": "http://open-services.net/ns/core#",
              "schema": "http://schema.org/",
              "skos": "http://www.w3.org/2004/02/skos/core#",
              "schema:name": {
                "@type": "xsd:string"
              },
              "schema:description": {
                "@type": "xsd:string"
              },
              "skos:prefLabel": {
                "@type": "xsd:string"
              },
              "skos:altLabel": {
                "@type": "xsd:string"
              },
              "pav:createdOn": {
                "@type": "xsd:dateTime"
              },
              "pav:createdBy": {
                "@type": "@id"
              },
              "pav:lastUpdatedOn": {
                "@type": "xsd:dateTime"
              },
              "oslc:modifiedBy": {
                "@type": "@id"
              }
            },
            "type": "object",
            "title": "westBoundLongitude field schema",
            "description": "westBoundLongitude field schema generated by the CEDAR Template Editor 2.5.11",
            "_ui": {
              "inputType": "textfield"
            },
            "_valueConstraints": {
              "requiredValue": true
            },
            "properties": {
              "@type": {
                "oneOf": [
                  {
                    "type": "string",
                    "format": "uri"
                  },
                  {
                    "type": "array",
                    "minItems": 1,
                    "items": {
                      "type": "string",
                      "format": "uri"
                    },
                    "uniqueItems": true
                  }
                ]
              },
              "@value": {
                "type": [
                  "string",
                  "null"
                ]
              },
              "rdfs:label": {
                "type": [
                  "string",
                  "null"
                ]
              }
            },
            "required": [
              "@value"
            ],
            "schema:name": "westBoundLongitude",
            "schema:description": "The most west longitude of a bounding box representing an area of dataset collection.",
            "pav:createdOn": "2020-10-20T09:48:15-07:00",
            "pav:createdBy": "https://metadatacenter.org/users/cb584e9d-cd34-44f0-9d67-10b217311750",
            "pav:lastUpdatedOn": "2020-10-20T09:48:15-07:00",
            "oslc:modifiedBy": "https://metadatacenter.org/users/cb584e9d-cd34-44f0-9d67-10b217311750",
            "schema:schemaVersion": "1.6.0",
            "additionalProperties": false,
            "skos:prefLabel": "westBoundLongitude",
            "@id": "https://repo.metadatacenter.org/template-fields/767548fe-5241-4acb-8223-194092781f15",
            "$schema": "http://json-schema.org/draft-04/schema#"
          },
          "eastBoundLongitude": {
            "@type": "https://schema.metadatacenter.org/core/TemplateField",
            "@context": {
              "xsd": "http://www.w3.org/2001/XMLSchema#",
              "pav": "http://purl.org/pav/",
              "bibo": "http://purl.org/ontology/bibo/",
              "oslc": "http://open-services.net/ns/core#",
              "schema": "http://schema.org/",
              "skos": "http://www.w3.org/2004/02/skos/core#",
              "schema:name": {
                "@type": "xsd:string"
              },
              "schema:description": {
                "@type": "xsd:string"
              },
              "skos:prefLabel": {
                "@type": "xsd:string"
              },
              "skos:altLabel": {
                "@type": "xsd:string"
              },
              "pav:createdOn": {
                "@type": "xsd:dateTime"
              },
              "pav:createdBy": {
                "@type": "@id"
              },
              "pav:lastUpdatedOn": {
                "@type": "xsd:dateTime"
              },
              "oslc:modifiedBy": {
                "@type": "@id"
              }
            },
            "type": "object",
            "title": "eastBoundLongitude field schema",
            "description": "eastBoundLongitude field schema generated by the CEDAR Template Editor 2.5.11",
            "_ui": {
              "inputType": "textfield"
            },
            "_valueConstraints": {
              "requiredValue": true
            },
            "properties": {
              "@type": {
                "oneOf": [
                  {
                    "type": "string",
                    "format": "uri"
                  },
                  {
                    "type": "array",
                    "minItems": 1,
                    "items": {
                      "type": "string",
                      "format": "uri"
                    },
                    "uniqueItems": true
                  }
                ]
              },
              "@value": {
                "type": [
                  "string",
                  "null"
                ]
              },
              "rdfs:label": {
                "type": [
                  "string",
                  "null"
                ]
              }
            },
            "required": [
              "@value"
            ],
            "schema:name": "eastBoundLongitude",
            "schema:description": "The most east longitude of a bounding box representing an area of dataset collection.",
            "pav:createdOn": "2020-10-20T09:48:15-07:00",
            "pav:createdBy": "https://metadatacenter.org/users/cb584e9d-cd34-44f0-9d67-10b217311750",
            "pav:lastUpdatedOn": "2020-10-20T09:48:15-07:00",
            "oslc:modifiedBy": "https://metadatacenter.org/users/cb584e9d-cd34-44f0-9d67-10b217311750",
            "schema:schemaVersion": "1.6.0",
            "additionalProperties": false,
            "skos:prefLabel": "eastBoundLongitude",
            "@id": "https://repo.metadatacenter.org/template-fields/ccf9a902-31ce-4188-9ce6-232e429710ae",
            "$schema": "http://json-schema.org/draft-04/schema#"
          },
          "southBoundLatitude": {
            "@type": "https://schema.metadatacenter.org/core/TemplateField",
            "@context": {
              "xsd": "http://www.w3.org/2001/XMLSchema#",
              "pav": "http://purl.org/pav/",
              "bibo": "http://purl.org/ontology/bibo/",
              "oslc": "http://open-services.net/ns/core#",
              "schema": "http://schema.org/",
              "skos": "http://www.w3.org/2004/02/skos/core#",
              "schema:name": {
                "@type": "xsd:string"
              },
              "schema:description": {
                "@type": "xsd:string"
              },
              "skos:prefLabel": {
                "@type": "xsd:string"
              },
              "skos:altLabel": {
                "@type": "xsd:string"
              },
              "pav:createdOn": {
                "@type": "xsd:dateTime"
              },
              "pav:createdBy": {
                "@type": "@id"
              },
              "pav:lastUpdatedOn": {
                "@type": "xsd:dateTime"
              },
              "oslc:modifiedBy": {
                "@type": "@id"
              }
            },
            "type": "object",
            "title": "southBoundLatitude field schema",
            "description": "southBoundLatitude field schema generated by the CEDAR Template Editor 2.5.11",
            "_ui": {
              "inputType": "textfield"
            },
            "_valueConstraints": {
              "requiredValue": true
            },
            "properties": {
              "@type": {
                "oneOf": [
                  {
                    "type": "string",
                    "format": "uri"
                  },
                  {
                    "type": "array",
                    "minItems": 1,
                    "items": {
                      "type": "string",
                      "format": "uri"
                    },
                    "uniqueItems": true
                  }
                ]
              },
              "@value": {
                "type": [
                  "string",
                  "null"
                ]
              },
              "rdfs:label": {
                "type": [
                  "string",
                  "null"
                ]
              }
            },
            "required": [
              "@value"
            ],
            "schema:name": "southBoundLatitude",
            "schema:description": "The most south latitude of a bounding box representing an area of dataset collection.",
            "pav:createdOn": "2020-10-20T09:48:15-07:00",
            "pav:createdBy": "https://metadatacenter.org/users/cb584e9d-cd34-44f0-9d67-10b217311750",
            "pav:lastUpdatedOn": "2020-10-20T09:48:15-07:00",
            "oslc:modifiedBy": "https://metadatacenter.org/users/cb584e9d-cd34-44f0-9d67-10b217311750",
            "schema:schemaVersion": "1.6.0",
            "additionalProperties": false,
            "skos:prefLabel": "southBoundLatitude",
            "@id": "https://repo.metadatacenter.org/template-fields/3f76c06e-cb7e-423e-93b2-f43c31520262",
            "$schema": "http://json-schema.org/draft-04/schema#"
          },
          "northBoundLatitude": {
            "@type": "https://schema.metadatacenter.org/core/TemplateField",
            "@context": {
              "xsd": "http://www.w3.org/2001/XMLSchema#",
              "pav": "http://purl.org/pav/",
              "bibo": "http://purl.org/ontology/bibo/",
              "oslc": "http://open-services.net/ns/core#",
              "schema": "http://schema.org/",
              "skos": "http://www.w3.org/2004/02/skos/core#",
              "schema:name": {
                "@type": "xsd:string"
              },
              "schema:description": {
                "@type": "xsd:string"
              },
              "skos:prefLabel": {
                "@type": "xsd:string"
              },
              "skos:altLabel": {
                "@type": "xsd:string"
              },
              "pav:createdOn": {
                "@type": "xsd:dateTime"
              },
              "pav:createdBy": {
                "@type": "@id"
              },
              "pav:lastUpdatedOn": {
                "@type": "xsd:dateTime"
              },
              "oslc:modifiedBy": {
                "@type": "@id"
              }
            },
            "type": "object",
            "title": "northBoundLatitude field schema",
            "description": "northBoundLatitude field schema generated by the CEDAR Template Editor 2.5.11",
            "_ui": {
              "inputType": "textfield"
            },
            "_valueConstraints": {
              "requiredValue": true
            },
            "properties": {
              "@type": {
                "oneOf": [
                  {
                    "type": "string",
                    "format": "uri"
                  },
                  {
                    "type": "array",
                    "minItems": 1,
                    "items": {
                      "type": "string",
                      "format": "uri"
                    },
                    "uniqueItems": true
                  }
                ]
              },
              "@value": {
                "type": [
                  "string",
                  "null"
                ]
              },
              "rdfs:label": {
                "type": [
                  "string",
                  "null"
                ]
              }
            },
            "required": [
              "@value"
            ],
            "schema:name": "northBoundLatitude",
            "schema:description": "The most north latitude of a bounding box representing an area of dataset collection.",
            "pav:createdOn": "2020-10-20T09:48:15-07:00",
            "pav:createdBy": "https://metadatacenter.org/users/cb584e9d-cd34-44f0-9d67-10b217311750",
            "pav:lastUpdatedOn": "2020-10-20T09:48:15-07:00",
            "oslc:modifiedBy": "https://metadatacenter.org/users/cb584e9d-cd34-44f0-9d67-10b217311750",
            "schema:schemaVersion": "1.6.0",
            "additionalProperties": false,
            "skos:prefLabel": "northBoundLatitude",
            "@id": "https://repo.metadatacenter.org/template-fields/2d93e56e-69c6-41c4-9820-8b9dff6aa31d",
            "$schema": "http://json-schema.org/draft-04/schema#"
          }
        },
        "required": [
          "@context",
          "@id",
          "westBoundLongitude",
          "eastBoundLongitude",
          "southBoundLatitude",
          "northBoundLatitude"
        ],
        "additionalProperties": false,
        "pav:createdOn": "2020-10-20T09:54:21-07:00",
        "pav:createdBy": "https://metadatacenter.org/users/cb584e9d-cd34-44f0-9d67-10b217311750",
        "pav:lastUpdatedOn": "2020-10-20T09:54:21-07:00",
        "oslc:modifiedBy": "https://metadatacenter.org/users/cb584e9d-cd34-44f0-9d67-10b217311750",
        "schema:schemaVersion": "1.6.0",
        "schema:name": "SpatialCoverageBoundingBox",
        "schema:description": "The geospatial area (region on Earth) covered by the dataset being described.",
        "pav:version": "0.0.1",
        "bibo:status": "bibo:draft",
        "$schema": "http://json-schema.org/draft-04/schema#"
      }
    },
    "SpatialCoveragePolygon": {
      "type": "array",
      "minItems": 0,
      "maxItems": 1,
      "items": {
        "type": "object",
        "@id": "https://repo.metadatacenter.org/template-elements/09c7d036-870e-4e98-ae5e-fed158de1a57",
        "@type": "https://schema.metadatacenter.org/core/TemplateElement",
        "@context": {
          "xsd": "http://www.w3.org/2001/XMLSchema#",
          "pav": "http://purl.org/pav/",
          "bibo": "http://purl.org/ontology/bibo/",
          "oslc": "http://open-services.net/ns/core#",
          "schema": "http://schema.org/",
          "schema:name": {
            "@type": "xsd:string"
          },
          "schema:description": {
            "@type": "xsd:string"
          },
          "pav:createdOn": {
            "@type": "xsd:dateTime"
          },
          "pav:createdBy": {
            "@type": "@id"
          },
          "pav:lastUpdatedOn": {
            "@type": "xsd:dateTime"
          },
          "oslc:modifiedBy": {
            "@type": "@id"
          }
        },
        "title": "SpatialCoveragePolygon field schema",
        "description": "SpatialCoveragePolygon field schema generated by the CEDAR Template Editor 2.5.11",
        "_ui": {
          "order": [
            "SpatialCoveragePoints"
          ],
          "propertyLabels": {
            "SpatialCoveragePoints": "SpatialCoveragePoints"
          },
          "propertyDescriptions": {
            "SpatialCoveragePoints": "The geospatial area (region on Earth) covered by the dataset being described."
          }
        },
        "properties": {
          "@context": {
            "type": "object",
            "properties": {
              "SpatialCoveragePoints": {
                "enum": [
                  "https://schema.metadatacenter.org/properties/fbbdbc1d-1b6d-4ac5-b7c4-497a1e7eec8c"
                ]
              }
            },
            "additionalProperties": false,
            "required": [
              "SpatialCoveragePoints"
            ]
          },
          "@id": {
            "type": "string",
            "format": "uri"
          },
          "@type": {
            "oneOf": [
              {
                "type": "string",
                "format": "uri"
              },
              {
                "type": "array",
                "minItems": 1,
                "items": {
                  "type": "string",
                  "format": "uri"
                },
                "uniqueItems": true
              }
            ]
          },
          "SpatialCoveragePoints": {
            "type": "array",
            "minItems": 3,
            "items": {
              "type": "object",
              "@id": "https://repo.metadatacenter.org/template-elements/d89927c0-4708-4845-b31c-4ce3e6b2a068",
              "@type": "https://schema.metadatacenter.org/core/TemplateElement",
              "@context": {
                "xsd": "http://www.w3.org/2001/XMLSchema#",
                "pav": "http://purl.org/pav/",
                "bibo": "http://purl.org/ontology/bibo/",
                "oslc": "http://open-services.net/ns/core#",
                "schema": "http://schema.org/",
                "schema:name": {
                  "@type": "xsd:string"
                },
                "schema:description": {
                  "@type": "xsd:string"
                },
                "pav:createdOn": {
                  "@type": "xsd:dateTime"
                },
                "pav:createdBy": {
                  "@type": "@id"
                },
                "pav:lastUpdatedOn": {
                  "@type": "xsd:dateTime"
                },
                "oslc:modifiedBy": {
                  "@type": "@id"
                }
              },
              "title": "SpatialCoveragePoints field schema",
              "description": "SpatialCoveragePoints field schema generated by the CEDAR Template Editor 2.5.11",
              "_ui": {
                "order": [
                  "pointLongitude",
                  "pointLatitude"
                ],
                "propertyLabels": {
                  "pointLongitude": "pointLongitude",
                  "pointLatitude": "pointLatitude"
                },
                "propertyDescriptions": {
                  "pointLongitude": "Geographic longitude of a point which represents a location of dataset collection.",
                  "pointLatitude": "Geographic latitude of a point which represents a location of dataset collection."
                }
              },
              "properties": {
                "@context": {
                  "type": "object",
                  "properties": {
                    "pointLongitude": {
                      "enum": [
                        "https://schema.metadatacenter.org/properties/4ba6f1f3-3895-40ae-90b5-0eb44e972c6d"
                      ]
                    },
                    "pointLatitude": {
                      "enum": [
                        "https://schema.metadatacenter.org/properties/f30f9128-f56d-4183-9b93-66b6349a2c40"
                      ]
                    }
                  },
                  "additionalProperties": false,
                  "required": [
                    "pointLongitude",
                    "pointLatitude"
                  ]
                },
                "@id": {
                  "type": "string",
                  "format": "uri"
                },
                "@type": {
                  "oneOf": [
                    {
                      "type": "string",
                      "format": "uri"
                    },
                    {
                      "type": "array",
                      "minItems": 1,
                      "items": {
                        "type": "string",
                        "format": "uri"
                      },
                      "uniqueItems": true
                    }
                  ]
                },
                "pointLongitude": {
                  "@type": "https://schema.metadatacenter.org/core/TemplateField",
                  "@context": {
                    "xsd": "http://www.w3.org/2001/XMLSchema#",
                    "pav": "http://purl.org/pav/",
                    "bibo": "http://purl.org/ontology/bibo/",
                    "oslc": "http://open-services.net/ns/core#",
                    "schema": "http://schema.org/",
                    "skos": "http://www.w3.org/2004/02/skos/core#",
                    "schema:name": {
                      "@type": "xsd:string"
                    },
                    "schema:description": {
                      "@type": "xsd:string"
                    },
                    "skos:prefLabel": {
                      "@type": "xsd:string"
                    },
                    "skos:altLabel": {
                      "@type": "xsd:string"
                    },
                    "pav:createdOn": {
                      "@type": "xsd:dateTime"
                    },
                    "pav:createdBy": {
                      "@type": "@id"
                    },
                    "pav:lastUpdatedOn": {
                      "@type": "xsd:dateTime"
                    },
                    "oslc:modifiedBy": {
                      "@type": "@id"
                    }
                  },
                  "type": "object",
                  "title": "pointLongitude field schema",
                  "description": "pointLongitude field schema generated by the CEDAR Template Editor 2.5.11",
                  "_ui": {
                    "inputType": "textfield"
                  },
                  "_valueConstraints": {
                    "requiredValue": true
                  },
                  "properties": {
                    "@type": {
                      "oneOf": [
                        {
                          "type": "string",
                          "format": "uri"
                        },
                        {
                          "type": "array",
                          "minItems": 1,
                          "items": {
                            "type": "string",
                            "format": "uri"
                          },
                          "uniqueItems": true
                        }
                      ]
                    },
                    "@value": {
                      "type": [
                        "string",
                        "null"
                      ]
                    },
                    "rdfs:label": {
                      "type": [
                        "string",
                        "null"
                      ]
                    }
                  },
                  "required": [
                    "@value"
                  ],
                  "schema:name": "pointLongitude",
                  "schema:description": "Geographic longitude of a point which represents a location of dataset collection.",
                  "pav:createdOn": "2020-10-20T09:46:22-07:00",
                  "pav:createdBy": "https://metadatacenter.org/users/cb584e9d-cd34-44f0-9d67-10b217311750",
                  "pav:lastUpdatedOn": "2020-10-20T09:46:22-07:00",
                  "oslc:modifiedBy": "https://metadatacenter.org/users/cb584e9d-cd34-44f0-9d67-10b217311750",
                  "schema:schemaVersion": "1.6.0",
                  "additionalProperties": false,
                  "skos:prefLabel": "pointLongitude",
                  "@id": "https://repo.metadatacenter.org/template-fields/2990d00b-1475-46d8-9116-e4e7e8349ac5",
                  "$schema": "http://json-schema.org/draft-04/schema#"
                },
                "pointLatitude": {
                  "@type": "https://schema.metadatacenter.org/core/TemplateField",
                  "@context": {
                    "xsd": "http://www.w3.org/2001/XMLSchema#",
                    "pav": "http://purl.org/pav/",
                    "bibo": "http://purl.org/ontology/bibo/",
                    "oslc": "http://open-services.net/ns/core#",
                    "schema": "http://schema.org/",
                    "skos": "http://www.w3.org/2004/02/skos/core#",
                    "schema:name": {
                      "@type": "xsd:string"
                    },
                    "schema:description": {
                      "@type": "xsd:string"
                    },
                    "skos:prefLabel": {
                      "@type": "xsd:string"
                    },
                    "skos:altLabel": {
                      "@type": "xsd:string"
                    },
                    "pav:createdOn": {
                      "@type": "xsd:dateTime"
                    },
                    "pav:createdBy": {
                      "@type": "@id"
                    },
                    "pav:lastUpdatedOn": {
                      "@type": "xsd:dateTime"
                    },
                    "oslc:modifiedBy": {
                      "@type": "@id"
                    }
                  },
                  "type": "object",
                  "title": "pointLatitude field schema",
                  "description": "pointLatitude field schema generated by the CEDAR Template Editor 2.5.11",
                  "_ui": {
                    "inputType": "textfield"
                  },
                  "_valueConstraints": {
                    "requiredValue": true
                  },
                  "properties": {
                    "@type": {
                      "oneOf": [
                        {
                          "type": "string",
                          "format": "uri"
                        },
                        {
                          "type": "array",
                          "minItems": 1,
                          "items": {
                            "type": "string",
                            "format": "uri"
                          },
                          "uniqueItems": true
                        }
                      ]
                    },
                    "@value": {
                      "type": [
                        "string",
                        "null"
                      ]
                    },
                    "rdfs:label": {
                      "type": [
                        "string",
                        "null"
                      ]
                    }
                  },
                  "required": [
                    "@value"
                  ],
                  "schema:name": "pointLatitude",
                  "schema:description": "Geographic latitude of a point which represents a location of dataset collection.",
                  "pav:createdOn": "2020-10-20T09:46:22-07:00",
                  "pav:createdBy": "https://metadatacenter.org/users/cb584e9d-cd34-44f0-9d67-10b217311750",
                  "pav:lastUpdatedOn": "2020-10-20T09:46:22-07:00",
                  "oslc:modifiedBy": "https://metadatacenter.org/users/cb584e9d-cd34-44f0-9d67-10b217311750",
                  "schema:schemaVersion": "1.6.0",
                  "additionalProperties": false,
                  "skos:prefLabel": "pointLatitude",
                  "@id": "https://repo.metadatacenter.org/template-fields/6ba76c6e-9f3a-46a0-b625-acb57f8c1716",
                  "$schema": "http://json-schema.org/draft-04/schema#"
                }
              },
              "required": [
                "@context",
                "@id",
                "pointLongitude",
                "pointLatitude"
              ],
              "additionalProperties": false,
              "pav:createdOn": "2020-10-20T09:51:46-07:00",
              "pav:createdBy": "https://metadatacenter.org/users/cb584e9d-cd34-44f0-9d67-10b217311750",
              "pav:lastUpdatedOn": "2020-10-20T09:51:46-07:00",
              "oslc:modifiedBy": "https://metadatacenter.org/users/cb584e9d-cd34-44f0-9d67-10b217311750",
              "schema:schemaVersion": "1.6.0",
              "schema:name": "SpatialCoveragePoints",
              "schema:description": "The geospatial area (region on Earth) covered by the dataset being described.",
              "pav:version": "0.0.1",
              "bibo:status": "bibo:draft",
              "$schema": "http://json-schema.org/draft-04/schema#"
            }
          }
        },
        "required": [
          "@context",
          "@id",
          "SpatialCoveragePoints"
        ],
        "additionalProperties": false,
        "pav:createdOn": "2020-10-20T09:54:21-07:00",
        "pav:createdBy": "https://metadatacenter.org/users/cb584e9d-cd34-44f0-9d67-10b217311750",
        "pav:lastUpdatedOn": "2020-10-20T09:54:21-07:00",
        "oslc:modifiedBy": "https://metadatacenter.org/users/cb584e9d-cd34-44f0-9d67-10b217311750",
        "schema:schemaVersion": "1.6.0",
        "schema:name": "SpatialCoveragePolygon",
        "schema:description": "The geospatial area (region on Earth) covered by the dataset described by a polygon.",
        "pav:version": "0.0.1",
        "bibo:status": "bibo:draft",
        "$schema": "http://json-schema.org/draft-04/schema#"
      }
    },
    "GeoLocations": {
      "type": "array",
      "minItems": 0,
      "items": {
        "type": "object",
        "@id": "https://repo.metadatacenter.org/template-elements/f57ffbbc-4f13-4bb7-8085-3db785cd252e",
        "@type": "https://schema.metadatacenter.org/core/TemplateElement",
        "@context": {
          "xsd": "http://www.w3.org/2001/XMLSchema#",
          "pav": "http://purl.org/pav/",
          "bibo": "http://purl.org/ontology/bibo/",
          "oslc": "http://open-services.net/ns/core#",
          "schema": "http://schema.org/",
          "schema:name": {
            "@type": "xsd:string"
          },
          "schema:description": {
            "@type": "xsd:string"
          },
          "pav:createdOn": {
            "@type": "xsd:dateTime"
          },
          "pav:createdBy": {
            "@type": "@id"
          },
          "pav:lastUpdatedOn": {
            "@type": "xsd:dateTime"
          },
          "oslc:modifiedBy": {
            "@type": "@id"
          }
        },
        "title": "GeoLocations field schema",
        "description": "GeoLocations field schema generated by the CEDAR Template Editor 2.5.11",
        "_ui": {
          "order": [
            "geoLocationPlace"
          ],
          "propertyLabels": {
            "geoLocationPlace": "geoLocationPlace"
          },
          "propertyDescriptions": {
            "geoLocationPlace": "The description of a geographical location of dataset collection."
          }
        },
        "properties": {
          "@context": {
            "type": "object",
            "properties": {
              "geoLocationPlace": {
                "enum": [
                  "https://schema.metadatacenter.org/properties/bb4f4aef-c396-4389-8c5e-579aa5609536"
                ]
              }
            },
            "additionalProperties": false,
            "required": [
              "geoLocationPlace"
            ]
          },
          "@id": {
            "type": "string",
            "format": "uri"
          },
          "@type": {
            "oneOf": [
              {
                "type": "string",
                "format": "uri"
              },
              {
                "type": "array",
                "minItems": 1,
                "items": {
                  "type": "string",
                  "format": "uri"
                },
                "uniqueItems": true
              }
            ]
          },
          "geoLocationPlace": {
            "type": "array",
            "minItems": 1,
            "items": {
              "type": "object",
              "@type": "https://schema.metadatacenter.org/core/TemplateField",
              "@context": {
                "xsd": "http://www.w3.org/2001/XMLSchema#",
                "pav": "http://purl.org/pav/",
                "bibo": "http://purl.org/ontology/bibo/",
                "oslc": "http://open-services.net/ns/core#",
                "schema": "http://schema.org/",
                "skos": "http://www.w3.org/2004/02/skos/core#",
                "schema:name": {
                  "@type": "xsd:string"
                },
                "schema:description": {
                  "@type": "xsd:string"
                },
                "skos:prefLabel": {
                  "@type": "xsd:string"
                },
                "skos:altLabel": {
                  "@type": "xsd:string"
                },
                "pav:createdOn": {
                  "@type": "xsd:dateTime"
                },
                "pav:createdBy": {
                  "@type": "@id"
                },
                "pav:lastUpdatedOn": {
                  "@type": "xsd:dateTime"
                },
                "oslc:modifiedBy": {
                  "@type": "@id"
                }
              },
              "title": "geoLocationPlace field schema",
              "description": "geoLocationPlace field schema generated by the CEDAR Template Editor 2.5.11",
              "_ui": {
                "inputType": "textfield"
              },
              "_valueConstraints": {
                "requiredValue": false
              },
              "properties": {
                "@type": {
                  "oneOf": [
                    {
                      "type": "string",
                      "format": "uri"
                    },
                    {
                      "type": "array",
                      "minItems": 1,
                      "items": {
                        "type": "string",
                        "format": "uri"
                      },
                      "uniqueItems": true
                    }
                  ]
                },
                "@value": {
                  "type": [
                    "string",
                    "null"
                  ]
                },
                "rdfs:label": {
                  "type": [
                    "string",
                    "null"
                  ]
                }
              },
              "required": [
                "@value"
              ],
              "additionalProperties": false,
              "pav:createdOn": "2020-10-20T09:53:32-07:00",
              "pav:createdBy": "https://metadatacenter.org/users/cb584e9d-cd34-44f0-9d67-10b217311750",
              "pav:lastUpdatedOn": "2020-10-20T09:53:32-07:00",
              "oslc:modifiedBy": "https://metadatacenter.org/users/cb584e9d-cd34-44f0-9d67-10b217311750",
              "schema:schemaVersion": "1.6.0",
              "schema:name": "geoLocationPlace",
              "schema:description": "The description of a geographical location of dataset collection.",
              "skos:prefLabel": "geoLocationPlace",
              "@id": "https://repo.metadatacenter.org/template-fields/5898ed2f-d6d2-40e8-a642-fc5fa510cf4e",
              "$schema": "http://json-schema.org/draft-04/schema#"
            }
          }
        },
        "required": [
          "@context",
          "@id",
          "geoLocationPlace"
        ],
        "additionalProperties": false,
        "pav:createdOn": "2020-10-20T09:54:21-07:00",
        "pav:createdBy": "https://metadatacenter.org/users/cb584e9d-cd34-44f0-9d67-10b217311750",
        "pav:lastUpdatedOn": "2020-10-20T09:54:21-07:00",
        "oslc:modifiedBy": "https://metadatacenter.org/users/cb584e9d-cd34-44f0-9d67-10b217311750",
        "schema:schemaVersion": "1.6.0",
        "schema:name": "GeoLocations",
        "schema:description": "Geo locations which are covered by the dataset being described.",
        "pav:version": "0.0.1",
        "bibo:status": "bibo:draft",
        "$schema": "http://json-schema.org/draft-04/schema#"
      }
    }
  },
  "schema:name": "SpatialCoverage",
  "schema:description": "The geospatial area (region on Earth) covered by the dataset being described.",
  "required": [
    "@context",
    "@id",
    "SpatialCoveragePoints",
    "SpatialCoverageBoundingBox",
    "SpatialCoveragePolygon",
    "GeoLocations"
  ],
  "pav:createdOn": "2020-10-20T09:50:44-07:00",
  "pav:createdBy": "https://metadatacenter.org/users/cb584e9d-cd34-44f0-9d67-10b217311750",
  "pav:lastUpdatedOn": "2020-10-20T09:54:21-07:00",
  "oslc:modifiedBy": "https://metadatacenter.org/users/cb584e9d-cd34-44f0-9d67-10b217311750",
  "schema:schemaVersion": "1.6.0",
  "additionalProperties": false,
  "pav:version": "0.0.1",
  "bibo:status": "bibo:draft",
  "$schema": "http://json-schema.org/draft-04/schema#"
}